{
  "Fuel": {
    "Type": [
      {
        "ACT": "20318",
        "CATEGORY": "Coal",
        "FUEL_CATEGORY": "Coal  (20,318 MW)",
        "INTERVALEST": "2023-08-31 10:05:00 AM"
      },
      {
        "ACT": "24567",
        "CATEGORY": "Natural Gas",
        "FUEL_CATEGORY": "Natural Gas  (24,567 MW)",
        "INTERVALEST": "2023-08-31 10:05:00 AM"
      },
      {
        "ACT": "10590",
        "CATEGORY": "Nuclear",
        "FUEL_CATEGORY": "Nuclear  (10,590 MW)",
        "INTERVALEST": "2023-08-31 10:05:00 AM"
      },
      {
        "ACT": "10461",
        "CATEGORY": "Wind",
        "FUEL_CATEGORY": "Wind  (10,461 MW)",
        "INTERVALEST": "2023-08-31 10:05:00 AM"
      },
      {
        "ACT": "3152",
        "CATEGORY": "Solar",
        "FUEL_CATEGORY": "Solar  (3,152 MW)",
        "INTERVALEST": "2023-08-31 10:05:00 AM"
      },
      {
        "ACT": "786",
        "CATEGORY": "Other",
        "FUEL_CATEGORY": "Other  (786 MW)",
        "INTERVALEST": "2023-08-31 10:05:00 AM"
      }
    ]
  },
  "RefId": "31-Aug-2023 - Interval 10:05 EST",
  "TotalMW": "69574"
}
