{
  "Fuel": {
    "Type": [
      {
        "ACT": "17277",
        "CATEGORY": "Coal",
        "FUEL_CATEGORY": "Coal  (17,277 MW)",
        "INTERVALEST": "2023-10-03 1:25:00 AM"
      },
      {
        "ACT": "16190",
        "CATEGORY": "Natural Gas",
        "FUEL_CATEGORY": "Natural Gas  (16,190 MW)",
        "INTERVALEST": "2023-10-03 1:25:00 AM"
      },
      {
        "ACT": "8718",
        "CATEGORY": "Nuclear",
        "FUEL_CATEGORY": "Nuclear  (8,718 MW)",
        "INTERVALEST": "2023-10-03 1:25:00 AM"
      },
      {
        "ACT": "16408",
        "CATEGORY": "Wind",
        "FUEL_CATEGORY": "Wind  (16,408 MW)",
        "INTERVALEST": "2023-10-03 1:25:00 AM"
      },
      {
        "ACT": "-1",
        "CATEGORY": "Solar",
        "FUEL_CATEGORY": "Solar  (-1 MW)",
        "INTERVALEST": "2023-10-03 1:25:00 AM"
      },
      {
        "ACT": "411",
        "CATEGORY": "Other",
        "FUEL_CATEGORY": "Other  (411 MW)",
        "INTERVALEST": "2023-10-03 1:25:00 AM"
      }
    ]
  },
  "RefId": "03-Oct-2023 - Interval 01:25 EST",
  "TotalMW": "59001"
}
