{
  "Fuel": {
    "Type": [
      {
        "ACT": "27746",
        "CATEGORY": "Coal",
        "FUEL_CATEGORY": "Coal  (27,746 MW)",
        "INTERVALEST": "2023-06-22 8:25:00 AM"
      },
      {
        "ACT": "28861",
        "CATEGORY": "Natural Gas",
        "FUEL_CATEGORY": "Natural Gas  (28,861 MW)",
        "INTERVALEST": "2023-06-22 8:25:00 AM"
      },
      {
        "ACT": "11653",
        "CATEGORY": "Nuclear",
        "FUEL_CATEGORY": "Nuclear  (11,653 MW)",
        "INTERVALEST": "2023-06-22 8:25:00 AM"
      },
      {
        "ACT": "2303",
        "CATEGORY": "Wind",
        "FUEL_CATEGORY": "Wind  (2,303 MW)",
        "INTERVALEST": "2023-06-22 8:25:00 AM"
      },
      {
        "ACT": "2198",
        "CATEGORY": "Solar",
        "FUEL_CATEGORY": "Solar  (2,198 MW)",
        "INTERVALEST": "2023-06-22 8:25:00 AM"
      },
      {
        "ACT": "789",
        "CATEGORY": "Other",
        "FUEL_CATEGORY": "Other  (789 MW)",
        "INTERVALEST": "2023-06-22 8:25:00 AM"
      }
    ]
  },
  "RefId": "22-Jun-2023 - Interval 08:25 EST",
  "TotalMW": "73558"
}
