{
  "Fuel": {
    "Type": [
      {
        "ACT": "15530",
        "CATEGORY": "Coal",
        "FUEL_CATEGORY": "Coal  (15,530 MW)",
        "INTERVALEST": "2023-02-11 3:20:00 PM"
      },
      {
        "ACT": "19288",
        "CATEGORY": "Natural Gas",
        "FUEL_CATEGORY": "Natural Gas  (19,288 MW)",
        "INTERVALEST": "2023-02-11 3:20:00 PM"
      },
      {
        "ACT": "11024",
        "CATEGORY": "Nuclear",
        "FUEL_CATEGORY": "Nuclear  (11,024 MW)",
        "INTERVALEST": "2023-02-11 3:20:00 PM"
      },
      {
        "ACT": "15451",
        "CATEGORY": "Wind",
        "FUEL_CATEGORY": "Wind  (15,451 MW)",
        "INTERVALEST": "2023-02-11 3:20:00 PM"
      },
      {
        "ACT": "2029",
        "CATEGORY": "Solar",
        "FUEL_CATEGORY": "Solar  (2,029 MW)",
        "INTERVALEST": "2023-02-11 3:20:00 PM"
      },
      {
        "ACT": "877",
        "CATEGORY": "Other",
        "FUEL_CATEGORY": "Other  (877 MW)",
        "INTERVALEST": "2023-02-11 3:20:00 PM"
      }
    ]
  },
  "RefId": "11-Feb-2023 - Interval 15:20 EST",
  "TotalMW": "64234"
}
