{
  "Fuel": {
    "Type": [
      {
        "ACT": "18229",
        "CATEGORY": "Coal",
        "FUEL_CATEGORY": "Coal  (18,229 MW)",
        "INTERVALEST": "2024-11-20 10:40:00 PM"
      },
      {
        "ACT": "21289",
        "CATEGORY": "Natural Gas",
        "FUEL_CATEGORY": "Natural Gas  (21,289 MW)",
        "INTERVALEST": "2024-11-20 10:40:00 PM"
      },
      {
        "ACT": "9896",
        "CATEGORY": "Nuclear",
        "FUEL_CATEGORY": "Nuclear  (9,896 MW)",
        "INTERVALEST": "2024-11-20 10:40:00 PM"
      },
      {
        "ACT": "19498",
        "CATEGORY": "Wind",
        "FUEL_CATEGORY": "Wind  (19,498 MW)",
        "INTERVALEST": "2024-11-20 10:40:00 PM"
      },
      {
        "ACT": "87",
        "CATEGORY": "Solar",
        "FUEL_CATEGORY": "Solar  (87 MW)",
        "INTERVALEST": "2024-11-20 10:40:00 PM"
      },
      {
        "ACT": "948",
        "CATEGORY": "Other",
        "FUEL_CATEGORY": "Other  (948 MW)",
        "INTERVALEST": "2024-11-20 10:40:00 PM"
      },
      {
        "ACT": "2761",
        "CATEGORY": "Imports",
        "FUEL_CATEGORY": "Imports (2,761.00 MW)",
        "INTERVALEST": "2024-11-20 10:40:00 PM"
      }
    ]
  },
  "RefId": "20-Nov-2024 - Interval 22:40 EST",
  "TotalMW": "72666"
}
