{
  "Fuel": {
    "Type": [
      {
        "ACT": "13515",
        "CATEGORY": "Coal",
        "FUEL_CATEGORY": "Coal  (13,515 MW)",
        "INTERVALEST": "2024-10-27 3:35:00 AM"
      },
      {
        "ACT": "18413",
        "CATEGORY": "Natural Gas",
        "FUEL_CATEGORY": "Natural Gas  (18,413 MW)",
        "INTERVALEST": "2024-10-27 3:35:00 AM"
      },
      {
        "ACT": "9617",
        "CATEGORY": "Nuclear",
        "FUEL_CATEGORY": "Nuclear  (9,617 MW)",
        "INTERVALEST": "2024-10-27 3:35:00 AM"
      },
      {
        "ACT": "15279",
        "CATEGORY": "Wind",
        "FUEL_CATEGORY": "Wind  (15,279 MW)",
        "INTERVALEST": "2024-10-27 3:35:00 AM"
      },
      {
        "ACT": "-4",
        "CATEGORY": "Solar",
        "FUEL_CATEGORY": "Solar  (-4 MW)",
        "INTERVALEST": "2024-10-27 3:35:00 AM"
      },
      {
        "ACT": "-295",
        "CATEGORY": "Other",
        "FUEL_CATEGORY": "Other  (-295 MW)",
        "INTERVALEST": "2024-10-27 3:35:00 AM"
      },
      {
        "ACT": "394",
        "CATEGORY": "Imports",
        "FUEL_CATEGORY": "Imports (394.00 MW)",
        "INTERVALEST": "2024-10-27 3:35:00 AM"
      }
    ]
  },
  "RefId": "27-Oct-2024 - Interval 03:35 EST",
  "TotalMW": "56972"
}
