{
  "Fuel": {
    "Type": [
      {
        "ACT": "16300",
        "CATEGORY": "Coal",
        "FUEL_CATEGORY": "Coal  (16,300 MW)",
        "INTERVALEST": "2024-03-24 6:30:00 PM"
      },
      {
        "ACT": "19993",
        "CATEGORY": "Natural Gas",
        "FUEL_CATEGORY": "Natural Gas  (19,993 MW)",
        "INTERVALEST": "2024-03-24 6:30:00 PM"
      },
      {
        "ACT": "8180",
        "CATEGORY": "Nuclear",
        "FUEL_CATEGORY": "Nuclear  (8,180 MW)",
        "INTERVALEST": "2024-03-24 6:30:00 PM"
      },
      {
        "ACT": "22412",
        "CATEGORY": "Wind",
        "FUEL_CATEGORY": "Wind  (22,412 MW)",
        "INTERVALEST": "2024-03-24 6:30:00 PM"
      },
      {
        "ACT": "405",
        "CATEGORY": "Solar",
        "FUEL_CATEGORY": "Solar  (405 MW)",
        "INTERVALEST": "2024-03-24 6:30:00 PM"
      },
      {
        "ACT": "1361",
        "CATEGORY": "Other",
        "FUEL_CATEGORY": "Other  (1,361 MW)",
        "INTERVALEST": "2024-03-24 6:30:00 PM"
      },
      {
        "ACT": "429",
        "CATEGORY": "Imports",
        "FUEL_CATEGORY": "Imports (429.00 MW)",
        "INTERVALEST": "2024-03-24 6:30:00 PM"
      }
    ]
  },
  "RefId": "24-Mar-2024 - Interval 18:30 EST",
  "TotalMW": "69079"
}
