{
  "Fuel": {
    "Type": [
      {
        "ACT": "29378",
        "CATEGORY": "Coal",
        "FUEL_CATEGORY": "Coal  (29,378 MW)",
        "INTERVALEST": "2024-01-05 11:45:00 PM"
      },
      {
        "ACT": "29744",
        "CATEGORY": "Natural Gas",
        "FUEL_CATEGORY": "Natural Gas  (29,744 MW)",
        "INTERVALEST": "2024-01-05 11:45:00 PM"
      },
      {
        "ACT": "9246",
        "CATEGORY": "Nuclear",
        "FUEL_CATEGORY": "Nuclear  (9,246 MW)",
        "INTERVALEST": "2024-01-05 11:45:00 PM"
      },
      {
        "ACT": "5305",
        "CATEGORY": "Wind",
        "FUEL_CATEGORY": "Wind  (5,305 MW)",
        "INTERVALEST": "2024-01-05 11:45:00 PM"
      },
      {
        "ACT": "-1",
        "CATEGORY": "Solar",
        "FUEL_CATEGORY": "Solar  (-1 MW)",
        "INTERVALEST": "2024-01-05 11:45:00 PM"
      },
      {
        "ACT": "121",
        "CATEGORY": "Other",
        "FUEL_CATEGORY": "Other  (121 MW)",
        "INTERVALEST": "2024-01-05 11:45:00 PM"
      }
    ]
  },
  "RefId": "05-Jan-2024 - Interval 23:45 EST",
  "TotalMW": "73793"
}
