{
  "Fuel": {
    "Type": [
      {
        "ACT": "23229",
        "CATEGORY": "Coal",
        "FUEL_CATEGORY": "Coal  (23,229 MW)",
        "INTERVALEST": "2024-10-08 1:15:00 PM"
      },
      {
        "ACT": "23803",
        "CATEGORY": "Natural Gas",
        "FUEL_CATEGORY": "Natural Gas  (23,803 MW)",
        "INTERVALEST": "2024-10-08 1:15:00 PM"
      },
      {
        "ACT": "10132",
        "CATEGORY": "Nuclear",
        "FUEL_CATEGORY": "Nuclear  (10,132 MW)",
        "INTERVALEST": "2024-10-08 1:15:00 PM"
      },
      {
        "ACT": "3973",
        "CATEGORY": "Wind",
        "FUEL_CATEGORY": "Wind  (3,973 MW)",
        "INTERVALEST": "2024-10-08 1:15:00 PM"
      },
      {
        "ACT": "7326",
        "CATEGORY": "Solar",
        "FUEL_CATEGORY": "Solar  (7,326 MW)",
        "INTERVALEST": "2024-10-08 1:15:00 PM"
      },
      {
        "ACT": "1039",
        "CATEGORY": "Other",
        "FUEL_CATEGORY": "Other  (1,039 MW)",
        "INTERVALEST": "2024-10-08 1:15:00 PM"
      },
      {
        "ACT": "3511",
        "CATEGORY": "Imports",
        "FUEL_CATEGORY": "Imports (3,511.00 MW)",
        "INTERVALEST": "2024-10-08 1:15:00 PM"
      }
    ]
  },
  "RefId": "08-Oct-2024 - Interval 13:15 EST",
  "TotalMW": "73019"
}
