{
  "Fuel": {
    "Type": [
      {
        "ACT": "26862",
        "CATEGORY": "Coal",
        "FUEL_CATEGORY": "Coal  (26,862 MW)",
        "INTERVALEST": "2022-12-10 10:30:00 AM"
      },
      {
        "ACT": "22622",
        "CATEGORY": "Natural Gas",
        "FUEL_CATEGORY": "Natural Gas  (22,622 MW)",
        "INTERVALEST": "2022-12-10 10:30:00 AM"
      },
      {
        "ACT": "11119",
        "CATEGORY": "Nuclear",
        "FUEL_CATEGORY": "Nuclear  (11,119 MW)",
        "INTERVALEST": "2022-12-10 10:30:00 AM"
      },
      {
        "ACT": "3394",
        "CATEGORY": "Wind",
        "FUEL_CATEGORY": "Wind  (3,394 MW)",
        "INTERVALEST": "2022-12-10 10:30:00 AM"
      },
      {
        "ACT": "173",
        "CATEGORY": "Solar",
        "FUEL_CATEGORY": "Solar  (173 MW)",
        "INTERVALEST": "2022-12-10 10:30:00 AM"
      },
      {
        "ACT": "989",
        "CATEGORY": "Other",
        "FUEL_CATEGORY": "Other  (989 MW)",
        "INTERVALEST": "2022-12-10 10:30:00 AM"
      }
    ]
  },
  "RefId": "10-Dec-2022 - Interval 10:30 EST",
  "TotalMW": "65159"
}
