{
  "Fuel": {
    "Type": [
      {
        "ACT": "24383",
        "CATEGORY": "Coal",
        "FUEL_CATEGORY": "Coal  (24,383 MW)",
        "INTERVALEST": "2023-01-04 11:50:00 AM"
      },
      {
        "ACT": "21349",
        "CATEGORY": "Natural Gas",
        "FUEL_CATEGORY": "Natural Gas  (21,349 MW)",
        "INTERVALEST": "2023-01-04 11:50:00 AM"
      },
      {
        "ACT": "11751",
        "CATEGORY": "Nuclear",
        "FUEL_CATEGORY": "Nuclear  (11,751 MW)",
        "INTERVALEST": "2023-01-04 11:50:00 AM"
      },
      {
        "ACT": "11524",
        "CATEGORY": "Wind",
        "FUEL_CATEGORY": "Wind  (11,524 MW)",
        "INTERVALEST": "2023-01-04 11:50:00 AM"
      },
      {
        "ACT": "585",
        "CATEGORY": "Solar",
        "FUEL_CATEGORY": "Solar  (585 MW)",
        "INTERVALEST": "2023-01-04 11:50:00 AM"
      },
      {
        "ACT": "1224",
        "CATEGORY": "Other",
        "FUEL_CATEGORY": "Other  (1,224 MW)",
        "INTERVALEST": "2023-01-04 11:50:00 AM"
      }
    ]
  },
  "RefId": "04-Jan-2023 - Interval 11:50 EST",
  "TotalMW": "70816"
}
