{
  "Fuel": {
    "Type": [
      {
        "ACT": "17148",
        "CATEGORY": "Coal",
        "FUEL_CATEGORY": "Coal  (17,148 MW)",
        "INTERVALEST": "2023-02-07 12:35:00 PM"
      },
      {
        "ACT": "20944",
        "CATEGORY": "Natural Gas",
        "FUEL_CATEGORY": "Natural Gas  (20,944 MW)",
        "INTERVALEST": "2023-02-07 12:35:00 PM"
      },
      {
        "ACT": "11358",
        "CATEGORY": "Nuclear",
        "FUEL_CATEGORY": "Nuclear  (11,358 MW)",
        "INTERVALEST": "2023-02-07 12:35:00 PM"
      },
      {
        "ACT": "15350",
        "CATEGORY": "Wind",
        "FUEL_CATEGORY": "Wind  (15,350 MW)",
        "INTERVALEST": "2023-02-07 12:35:00 PM"
      },
      {
        "ACT": "1116",
        "CATEGORY": "Solar",
        "FUEL_CATEGORY": "Solar  (1,116 MW)",
        "INTERVALEST": "2023-02-07 12:35:00 PM"
      },
      {
        "ACT": "1216",
        "CATEGORY": "Other",
        "FUEL_CATEGORY": "Other  (1,216 MW)",
        "INTERVALEST": "2023-02-07 12:35:00 PM"
      }
    ]
  },
  "RefId": "07-Feb-2023 - Interval 12:35 EST",
  "TotalMW": "67130"
}
