{
  "RefId": "03-Feb-2024 - Interval 13:23 EST",
  "instance": [
    {
      "NSI": "-3475",
      "timestamp": "2024-02-02 13:25:00"
    },
    {
      "NSI": "-3475",
      "timestamp": "2024-02-02 13:30:00"
    },
    {
      "NSI": "-3475",
      "timestamp": "2024-02-02 13:35:00"
    },
    {
      "NSI": "-3475",
      "timestamp": "2024-02-02 13:40:00"
    },
    {
      "NSI": "-3475",
      "timestamp": "2024-02-02 13:45:00"
    },
    {
      "NSI": "-3475",
      "timestamp": "2024-02-02 13:50:00"
    },
    {
      "NSI": "-3475",
      "timestamp": "2024-02-02 13:55:00"
    },
    {
      "NSI": "-3592",
      "timestamp": "2024-02-02 14:00:00"
    },
    {
      "NSI": "-3708",
      "timestamp": "2024-02-02 14:05:00"
    },
    {
      "NSI": "-3708",
      "timestamp": "2024-02-02 14:10:00"
    },
    {
      "NSI": "-3708",
      "timestamp": "2024-02-02 14:15:00"
    },
    {
      "NSI": "-3708",
      "timestamp": "2024-02-02 14:20:00"
    },
    {
      "NSI": "-3708",
      "timestamp": "2024-02-02 14:25:00"
    },
    {
      "NSI": "-3508",
      "timestamp": "2024-02-02 14:30:00"
    },
    {
      "NSI": "-3308",
      "timestamp": "2024-02-02 14:35:00"
    },
    {
      "NSI": "-3308",
      "timestamp": "2024-02-02 14:40:00"
    },
    {
      "NSI": "-3508",
      "timestamp": "2024-02-02 14:45:00"
    },
    {
      "NSI": "-3708",
      "timestamp": "2024-02-02 14:50:00"
    },
    {
      "NSI": "-3708",
      "timestamp": "2024-02-02 14:55:00"
    },
    {
      "NSI": "-3846",
      "timestamp": "2024-02-02 15:00:00"
    },
    {
      "NSI": "-3983",
      "timestamp": "2024-02-02 15:05:00"
    },
    {
      "NSI": "-3983",
      "timestamp": "2024-02-02 15:10:00"
    },
    {
      "NSI": "-3983",
      "timestamp": "2024-02-02 15:15:00"
    },
    {
      "NSI": "-3983",
      "timestamp": "2024-02-02 15:20:00"
    },
    {
      "NSI": "-3983",
      "timestamp": "2024-02-02 15:25:00"
    },
    {
      "NSI": "-3985",
      "timestamp": "2024-02-02 15:30:00"
    },
    {
      "NSI": "-3987",
      "timestamp": "2024-02-02 15:35:00"
    },
    {
      "NSI": "-3987",
      "timestamp": "2024-02-02 15:40:00"
    },
    {
      "NSI": "-3937",
      "timestamp": "2024-02-02 15:45:00"
    },
    {
      "NSI": "-3887",
      "timestamp": "2024-02-02 15:50:00"
    },
    {
      "NSI": "-3887",
      "timestamp": "2024-02-02 15:55:00"
    },
    {
      "NSI": "-3890",
      "timestamp": "2024-02-02 16:00:00"
    },
    {
      "NSI": "-3892",
      "timestamp": "2024-02-02 16:05:00"
    },
    {
      "NSI": "-3892",
      "timestamp": "2024-02-02 16:10:00"
    },
    {
      "NSI": "-3942",
      "timestamp": "2024-02-02 16:15:00"
    },
    {
      "NSI": "-3992",
      "timestamp": "2024-02-02 16:20:00"
    },
    {
      "NSI": "-3992",
      "timestamp": "2024-02-02 16:30:00"
    },
    {
      "NSI": "-3992",
      "timestamp": "2024-02-02 16:35:00"
    },
    {
      "NSI": "-3992",
      "timestamp": "2024-02-02 16:40:00"
    },
    {
      "NSI": "-3792",
      "timestamp": "2024-02-02 16:45:00"
    },
    {
      "NSI": "-3592",
      "timestamp": "2024-02-02 16:50:00"
    },
    {
      "NSI": "-3592",
      "timestamp": "2024-02-02 16:55:00"
    },
    {
      "NSI": "-3435",
      "timestamp": "2024-02-02 17:00:00"
    },
    {
      "NSI": "-3278",
      "timestamp": "2024-02-02 17:05:00"
    },
    {
      "NSI": "-3278",
      "timestamp": "2024-02-02 17:10:00"
    },
    {
      "NSI": "-3553",
      "timestamp": "2024-02-02 17:15:00"
    },
    {
      "NSI": "-3828",
      "timestamp": "2024-02-02 17:20:00"
    },
    {
      "NSI": "-3828",
      "timestamp": "2024-02-02 17:25:00"
    },
    {
      "NSI": "-3828",
      "timestamp": "2024-02-02 17:30:00"
    },
    {
      "NSI": "-3828",
      "timestamp": "2024-02-02 17:35:00"
    },
    {
      "NSI": "-3828",
      "timestamp": "2024-02-02 17:40:00"
    },
    {
      "NSI": "-3828",
      "timestamp": "2024-02-02 17:45:00"
    },
    {
      "NSI": "-3828",
      "timestamp": "2024-02-02 17:50:00"
    },
    {
      "NSI": "-3798",
      "timestamp": "2024-02-02 17:55:00"
    },
    {
      "NSI": "-3883",
      "timestamp": "2024-02-02 18:00:00"
    },
    {
      "NSI": "-3977",
      "timestamp": "2024-02-02 18:05:00"
    },
    {
      "NSI": "-3977",
      "timestamp": "2024-02-02 18:10:00"
    },
    {
      "NSI": "-3896",
      "timestamp": "2024-02-02 18:15:00"
    },
    {
      "NSI": "-3815",
      "timestamp": "2024-02-02 18:20:00"
    },
    {
      "NSI": "-3815",
      "timestamp": "2024-02-02 18:25:00"
    },
    {
      "NSI": "-3802",
      "timestamp": "2024-02-02 18:30:00"
    },
    {
      "NSI": "-3789",
      "timestamp": "2024-02-02 18:35:00"
    },
    {
      "NSI": "-3789",
      "timestamp": "2024-02-02 18:40:00"
    },
    {
      "NSI": "-3839",
      "timestamp": "2024-02-02 18:45:00"
    },
    {
      "NSI": "-3889",
      "timestamp": "2024-02-02 18:50:00"
    },
    {
      "NSI": "-3889",
      "timestamp": "2024-02-02 18:55:00"
    },
    {
      "NSI": "-3915",
      "timestamp": "2024-02-02 19:00:00"
    },
    {
      "NSI": "-3941",
      "timestamp": "2024-02-02 19:05:00"
    },
    {
      "NSI": "-3941",
      "timestamp": "2024-02-02 19:10:00"
    },
    {
      "NSI": "-3883",
      "timestamp": "2024-02-02 19:15:00"
    },
    {
      "NSI": "-3825",
      "timestamp": "2024-02-02 19:20:00"
    },
    {
      "NSI": "-3825",
      "timestamp": "2024-02-02 19:25:00"
    },
    {
      "NSI": "-3881",
      "timestamp": "2024-02-02 19:30:00"
    },
    {
      "NSI": "-3937",
      "timestamp": "2024-02-02 19:35:00"
    },
    {
      "NSI": "-3789",
      "timestamp": "2024-02-02 19:45:00"
    },
    {
      "NSI": "-3641",
      "timestamp": "2024-02-02 19:50:00"
    },
    {
      "NSI": "-3661",
      "timestamp": "2024-02-02 19:55:00"
    },
    {
      "NSI": "-3676",
      "timestamp": "2024-02-02 20:00:00"
    },
    {
      "NSI": "-3671",
      "timestamp": "2024-02-02 20:05:00"
    },
    {
      "NSI": "-3671",
      "timestamp": "2024-02-02 20:10:00"
    },
    {
      "NSI": "-3521",
      "timestamp": "2024-02-02 20:15:00"
    },
    {
      "NSI": "-3371",
      "timestamp": "2024-02-02 20:20:00"
    },
    {
      "NSI": "-3371",
      "timestamp": "2024-02-02 20:25:00"
    },
    {
      "NSI": "-3465",
      "timestamp": "2024-02-02 20:30:00"
    },
    {
      "NSI": "-3559",
      "timestamp": "2024-02-02 20:35:00"
    },
    {
      "NSI": "-3350",
      "timestamp": "2024-02-02 20:45:00"
    },
    {
      "NSI": "-3141",
      "timestamp": "2024-02-02 20:50:00"
    },
    {
      "NSI": "-2947",
      "timestamp": "2024-02-02 21:00:00"
    },
    {
      "NSI": "-2752",
      "timestamp": "2024-02-02 21:05:00"
    },
    {
      "NSI": "-2752",
      "timestamp": "2024-02-02 21:10:00"
    },
    {
      "NSI": "-2713",
      "timestamp": "2024-02-02 21:15:00"
    },
    {
      "NSI": "-2673",
      "timestamp": "2024-02-02 21:20:00"
    },
    {
      "NSI": "-2673",
      "timestamp": "2024-02-02 21:25:00"
    },
    {
      "NSI": "-2673",
      "timestamp": "2024-02-02 21:30:00"
    },
    {
      "NSI": "-2673",
      "timestamp": "2024-02-02 21:35:00"
    },
    {
      "NSI": "-2673",
      "timestamp": "2024-02-02 21:40:00"
    },
    {
      "NSI": "-2673",
      "timestamp": "2024-02-02 21:45:00"
    },
    {
      "NSI": "-2673",
      "timestamp": "2024-02-02 21:50:00"
    },
    {
      "NSI": "-2673",
      "timestamp": "2024-02-02 21:55:00"
    },
    {
      "NSI": "-2418",
      "timestamp": "2024-02-02 22:00:00"
    },
    {
      "NSI": "-2163",
      "timestamp": "2024-02-02 22:05:00"
    },
    {
      "NSI": "-2163",
      "timestamp": "2024-02-02 22:15:00"
    },
    {
      "NSI": "-2163",
      "timestamp": "2024-02-02 22:20:00"
    },
    {
      "NSI": "-2163",
      "timestamp": "2024-02-02 22:25:00"
    },
    {
      "NSI": "-2163",
      "timestamp": "2024-02-02 22:30:00"
    },
    {
      "NSI": "-2163",
      "timestamp": "2024-02-02 22:35:00"
    },
    {
      "NSI": "-2163",
      "timestamp": "2024-02-02 22:40:00"
    },
    {
      "NSI": "-2163",
      "timestamp": "2024-02-02 22:45:00"
    },
    {
      "NSI": "-2163",
      "timestamp": "2024-02-02 22:50:00"
    },
    {
      "NSI": "-2208",
      "timestamp": "2024-02-02 23:00:00"
    },
    {
      "NSI": "-2252",
      "timestamp": "2024-02-02 23:05:00"
    },
    {
      "NSI": "-2252",
      "timestamp": "2024-02-02 23:15:00"
    },
    {
      "NSI": "-2252",
      "timestamp": "2024-02-02 23:20:00"
    },
    {
      "NSI": "-2252",
      "timestamp": "2024-02-02 23:25:00"
    },
    {
      "NSI": "-2252",
      "timestamp": "2024-02-02 23:30:00"
    },
    {
      "NSI": "-2252",
      "timestamp": "2024-02-02 23:35:00"
    },
    {
      "NSI": "-2152",
      "timestamp": "2024-02-02 23:45:00"
    },
    {
      "NSI": "-2052",
      "timestamp": "2024-02-02 23:50:00"
    },
    {
      "NSI": "-2052",
      "timestamp": "2024-02-02 23:55:00"
    },
    {
      "NSI": "-1615",
      "timestamp": "2024-02-03 00:05:00"
    },
    {
      "NSI": "-1615",
      "timestamp": "2024-02-03 00:10:00"
    },
    {
      "NSI": "-1733",
      "timestamp": "2024-02-03 00:15:00"
    },
    {
      "NSI": "-1851",
      "timestamp": "2024-02-03 00:20:00"
    },
    {
      "NSI": "-1851",
      "timestamp": "2024-02-03 00:25:00"
    },
    {
      "NSI": "-1851",
      "timestamp": "2024-02-03 00:30:00"
    },
    {
      "NSI": "-1851",
      "timestamp": "2024-02-03 00:35:00"
    },
    {
      "NSI": "-1926",
      "timestamp": "2024-02-03 00:45:00"
    },
    {
      "NSI": "-2001",
      "timestamp": "2024-02-03 00:50:00"
    },
    {
      "NSI": "-2001",
      "timestamp": "2024-02-03 00:55:00"
    },
    {
      "NSI": "-2103",
      "timestamp": "2024-02-03 01:00:00"
    },
    {
      "NSI": "-2204",
      "timestamp": "2024-02-03 01:05:00"
    },
    {
      "NSI": "-2204",
      "timestamp": "2024-02-03 01:10:00"
    },
    {
      "NSI": "-2204",
      "timestamp": "2024-02-03 01:15:00"
    },
    {
      "NSI": "-2204",
      "timestamp": "2024-02-03 01:20:00"
    },
    {
      "NSI": "-2204",
      "timestamp": "2024-02-03 01:25:00"
    },
    {
      "NSI": "-2204",
      "timestamp": "2024-02-03 01:30:00"
    },
    {
      "NSI": "-2204",
      "timestamp": "2024-02-03 01:35:00"
    },
    {
      "NSI": "-2204",
      "timestamp": "2024-02-03 01:40:00"
    },
    {
      "NSI": "-2204",
      "timestamp": "2024-02-03 01:45:00"
    },
    {
      "NSI": "-2204",
      "timestamp": "2024-02-03 01:50:00"
    },
    {
      "NSI": "-2204",
      "timestamp": "2024-02-03 01:55:00"
    },
    {
      "NSI": "-2220",
      "timestamp": "2024-02-03 02:00:00"
    },
    {
      "NSI": "-2236",
      "timestamp": "2024-02-03 02:05:00"
    },
    {
      "NSI": "-2236",
      "timestamp": "2024-02-03 02:10:00"
    },
    {
      "NSI": "-2116",
      "timestamp": "2024-02-03 02:15:00"
    },
    {
      "NSI": "-1996",
      "timestamp": "2024-02-03 02:20:00"
    },
    {
      "NSI": "-1996",
      "timestamp": "2024-02-03 02:25:00"
    },
    {
      "NSI": "-1996",
      "timestamp": "2024-02-03 02:30:00"
    },
    {
      "NSI": "-1996",
      "timestamp": "2024-02-03 02:35:00"
    },
    {
      "NSI": "-1996",
      "timestamp": "2024-02-03 02:40:00"
    },
    {
      "NSI": "-2116",
      "timestamp": "2024-02-03 02:45:00"
    },
    {
      "NSI": "-2236",
      "timestamp": "2024-02-03 02:50:00"
    },
    {
      "NSI": "-2236",
      "timestamp": "2024-02-03 02:55:00"
    },
    {
      "NSI": "-2212",
      "timestamp": "2024-02-03 03:00:00"
    },
    {
      "NSI": "-2188",
      "timestamp": "2024-02-03 03:05:00"
    },
    {
      "NSI": "-2188",
      "timestamp": "2024-02-03 03:10:00"
    },
    {
      "NSI": "-2213",
      "timestamp": "2024-02-03 03:15:00"
    },
    {
      "NSI": "-2238",
      "timestamp": "2024-02-03 03:20:00"
    },
    {
      "NSI": "-2238",
      "timestamp": "2024-02-03 03:30:00"
    },
    {
      "NSI": "-2238",
      "timestamp": "2024-02-03 03:35:00"
    },
    {
      "NSI": "-2276",
      "timestamp": "2024-02-03 03:45:00"
    },
    {
      "NSI": "-2313",
      "timestamp": "2024-02-03 03:50:00"
    },
    {
      "NSI": "-2382",
      "timestamp": "2024-02-03 04:00:00"
    },
    {
      "NSI": "-2451",
      "timestamp": "2024-02-03 04:05:00"
    },
    {
      "NSI": "-2451",
      "timestamp": "2024-02-03 04:15:00"
    },
    {
      "NSI": "-2451",
      "timestamp": "2024-02-03 04:20:00"
    },
    {
      "NSI": "-2451",
      "timestamp": "2024-02-03 04:30:00"
    },
    {
      "NSI": "-2451",
      "timestamp": "2024-02-03 04:35:00"
    },
    {
      "NSI": "-2451",
      "timestamp": "2024-02-03 04:40:00"
    },
    {
      "NSI": "-2331",
      "timestamp": "2024-02-03 04:45:00"
    },
    {
      "NSI": "-2211",
      "timestamp": "2024-02-03 04:50:00"
    },
    {
      "NSI": "-2211",
      "timestamp": "2024-02-03 04:55:00"
    },
    {
      "NSI": "-2250",
      "timestamp": "2024-02-03 05:00:00"
    },
    {
      "NSI": "-2289",
      "timestamp": "2024-02-03 05:05:00"
    },
    {
      "NSI": "-2289",
      "timestamp": "2024-02-03 05:10:00"
    },
    {
      "NSI": "-2254",
      "timestamp": "2024-02-03 05:15:00"
    },
    {
      "NSI": "-2218",
      "timestamp": "2024-02-03 05:20:00"
    },
    {
      "NSI": "-2218",
      "timestamp": "2024-02-03 05:25:00"
    },
    {
      "NSI": "-2154",
      "timestamp": "2024-02-03 05:30:00"
    },
    {
      "NSI": "-2089",
      "timestamp": "2024-02-03 05:35:00"
    },
    {
      "NSI": "-2089",
      "timestamp": "2024-02-03 05:40:00"
    },
    {
      "NSI": "-2089",
      "timestamp": "2024-02-03 05:45:00"
    },
    {
      "NSI": "-2089",
      "timestamp": "2024-02-03 05:50:00"
    },
    {
      "NSI": "-2089",
      "timestamp": "2024-02-03 05:55:00"
    },
    {
      "NSI": "-1994",
      "timestamp": "2024-02-03 06:00:00"
    },
    {
      "NSI": "-1899",
      "timestamp": "2024-02-03 06:05:00"
    },
    {
      "NSI": "-1899",
      "timestamp": "2024-02-03 06:10:00"
    },
    {
      "NSI": "-1974",
      "timestamp": "2024-02-03 06:15:00"
    },
    {
      "NSI": "-2048",
      "timestamp": "2024-02-03 06:20:00"
    },
    {
      "NSI": "-2048",
      "timestamp": "2024-02-03 06:25:00"
    },
    {
      "NSI": "-1974",
      "timestamp": "2024-02-03 06:30:00"
    },
    {
      "NSI": "-1899",
      "timestamp": "2024-02-03 06:35:00"
    },
    {
      "NSI": "-1899",
      "timestamp": "2024-02-03 06:40:00"
    },
    {
      "NSI": "-1899",
      "timestamp": "2024-02-03 06:45:00"
    },
    {
      "NSI": "-1899",
      "timestamp": "2024-02-03 06:50:00"
    },
    {
      "NSI": "-1899",
      "timestamp": "2024-02-03 06:55:00"
    },
    {
      "NSI": "-2408",
      "timestamp": "2024-02-03 07:00:00"
    },
    {
      "NSI": "-2916",
      "timestamp": "2024-02-03 07:05:00"
    },
    {
      "NSI": "-2916",
      "timestamp": "2024-02-03 07:10:00"
    },
    {
      "NSI": "-3241",
      "timestamp": "2024-02-03 07:15:00"
    },
    {
      "NSI": "-3566",
      "timestamp": "2024-02-03 07:20:00"
    },
    {
      "NSI": "-3566",
      "timestamp": "2024-02-03 07:25:00"
    },
    {
      "NSI": "-3666",
      "timestamp": "2024-02-03 07:30:00"
    },
    {
      "NSI": "-3766",
      "timestamp": "2024-02-03 07:35:00"
    },
    {
      "NSI": "-3766",
      "timestamp": "2024-02-03 07:40:00"
    },
    {
      "NSI": "-3643",
      "timestamp": "2024-02-03 07:45:00"
    },
    {
      "NSI": "-3519",
      "timestamp": "2024-02-03 07:50:00"
    },
    {
      "NSI": "-3519",
      "timestamp": "2024-02-03 07:55:00"
    },
    {
      "NSI": "-3284",
      "timestamp": "2024-02-03 08:00:00"
    },
    {
      "NSI": "-3049",
      "timestamp": "2024-02-03 08:05:00"
    },
    {
      "NSI": "-3087",
      "timestamp": "2024-02-03 08:15:00"
    },
    {
      "NSI": "-3124",
      "timestamp": "2024-02-03 08:20:00"
    },
    {
      "NSI": "-3204",
      "timestamp": "2024-02-03 08:25:00"
    },
    {
      "NSI": "-3584",
      "timestamp": "2024-02-03 08:30:00"
    },
    {
      "NSI": "-3884",
      "timestamp": "2024-02-03 08:35:00"
    },
    {
      "NSI": "-3884",
      "timestamp": "2024-02-03 08:40:00"
    },
    {
      "NSI": "-3784",
      "timestamp": "2024-02-03 08:45:00"
    },
    {
      "NSI": "-3684",
      "timestamp": "2024-02-03 08:50:00"
    },
    {
      "NSI": "-3684",
      "timestamp": "2024-02-03 08:55:00"
    },
    {
      "NSI": "-3441",
      "timestamp": "2024-02-03 09:00:00"
    },
    {
      "NSI": "-3197",
      "timestamp": "2024-02-03 09:05:00"
    },
    {
      "NSI": "-3197",
      "timestamp": "2024-02-03 09:10:00"
    },
    {
      "NSI": "-3295",
      "timestamp": "2024-02-03 09:15:00"
    },
    {
      "NSI": "-3393",
      "timestamp": "2024-02-03 09:20:00"
    },
    {
      "NSI": "-3393",
      "timestamp": "2024-02-03 09:25:00"
    },
    {
      "NSI": "-3543",
      "timestamp": "2024-02-03 09:30:00"
    },
    {
      "NSI": "-3693",
      "timestamp": "2024-02-03 09:35:00"
    },
    {
      "NSI": "-3693",
      "timestamp": "2024-02-03 09:40:00"
    },
    {
      "NSI": "-3743",
      "timestamp": "2024-02-03 09:45:00"
    },
    {
      "NSI": "-3793",
      "timestamp": "2024-02-03 09:50:00"
    },
    {
      "NSI": "-3793",
      "timestamp": "2024-02-03 09:55:00"
    },
    {
      "NSI": "-4245",
      "timestamp": "2024-02-03 10:00:00"
    },
    {
      "NSI": "-4697",
      "timestamp": "2024-02-03 10:05:00"
    },
    {
      "NSI": "-4697",
      "timestamp": "2024-02-03 10:10:00"
    },
    {
      "NSI": "-4617",
      "timestamp": "2024-02-03 10:15:00"
    },
    {
      "NSI": "-4537",
      "timestamp": "2024-02-03 10:20:00"
    },
    {
      "NSI": "-4537",
      "timestamp": "2024-02-03 10:25:00"
    },
    {
      "NSI": "-4517",
      "timestamp": "2024-02-03 10:30:00"
    },
    {
      "NSI": "-4497",
      "timestamp": "2024-02-03 10:35:00"
    },
    {
      "NSI": "-4497",
      "timestamp": "2024-02-03 10:40:00"
    },
    {
      "NSI": "-4547",
      "timestamp": "2024-02-03 10:45:00"
    },
    {
      "NSI": "-4597",
      "timestamp": "2024-02-03 10:50:00"
    },
    {
      "NSI": "-4597",
      "timestamp": "2024-02-03 10:55:00"
    },
    {
      "NSI": "-5025",
      "timestamp": "2024-02-03 11:00:00"
    },
    {
      "NSI": "-5452",
      "timestamp": "2024-02-03 11:05:00"
    },
    {
      "NSI": "-5452",
      "timestamp": "2024-02-03 11:10:00"
    },
    {
      "NSI": "-5592",
      "timestamp": "2024-02-03 11:15:00"
    },
    {
      "NSI": "-5732",
      "timestamp": "2024-02-03 11:20:00"
    },
    {
      "NSI": "-5732",
      "timestamp": "2024-02-03 11:25:00"
    },
    {
      "NSI": "-5732",
      "timestamp": "2024-02-03 11:30:00"
    },
    {
      "NSI": "-5732",
      "timestamp": "2024-02-03 11:35:00"
    },
    {
      "NSI": "-5732",
      "timestamp": "2024-02-03 11:40:00"
    },
    {
      "NSI": "-5732",
      "timestamp": "2024-02-03 11:45:00"
    },
    {
      "NSI": "-5732",
      "timestamp": "2024-02-03 11:50:00"
    },
    {
      "NSI": "-5732",
      "timestamp": "2024-02-03 11:55:00"
    },
    {
      "NSI": "-5784",
      "timestamp": "2024-02-03 12:00:00"
    },
    {
      "NSI": "-5836",
      "timestamp": "2024-02-03 12:05:00"
    },
    {
      "NSI": "-5836",
      "timestamp": "2024-02-03 12:10:00"
    },
    {
      "NSI": "-5801",
      "timestamp": "2024-02-03 12:15:00"
    },
    {
      "NSI": "-5766",
      "timestamp": "2024-02-03 12:20:00"
    },
    {
      "NSI": "-5766",
      "timestamp": "2024-02-03 12:25:00"
    },
    {
      "NSI": "-5691",
      "timestamp": "2024-02-03 12:30:00"
    },
    {
      "NSI": "-5616",
      "timestamp": "2024-02-03 12:35:00"
    },
    {
      "NSI": "-5616",
      "timestamp": "2024-02-03 12:40:00"
    },
    {
      "NSI": "-5616",
      "timestamp": "2024-02-03 12:45:00"
    },
    {
      "NSI": "-5616",
      "timestamp": "2024-02-03 12:50:00"
    },
    {
      "NSI": "-5616",
      "timestamp": "2024-02-03 12:55:00"
    },
    {
      "NSI": "-5740",
      "timestamp": "2024-02-03 13:00:00"
    },
    {
      "NSI": "-5864",
      "timestamp": "2024-02-03 13:05:00"
    },
    {
      "NSI": "-5864",
      "timestamp": "2024-02-03 13:10:00"
    },
    {
      "NSI": "-5734",
      "timestamp": "2024-02-03 13:15:00"
    },
    {
      "NSI": "-5604",
      "timestamp": "2024-02-03 13:20:00"
    }
  ]
}
